dap_types/__init__.py
dap_types-20250315!1.70.post1.dist-info/METADATA
dap_types-20250315!1.70.post1.dist-info/WHEEL
dap_types-20250315!1.70.post1.dist-info/licenses/LICENSE
dap_types-20250315!1.70.post1.dist-info/RECORD
