Metadata-Version: 2.4
Name: dap-types
Version: 20250315!1.70.post1
Summary: Debugger Adapter Protocol types for Python.
License-File: LICENSE
Requires-Python: >=3.10
Requires-Dist: pydantic>=2.10.6
